odoo9_addon_analytic_base_department-9.0.1.0.0.99.dev17-py3.8-nspkg.pth
odoo_addons/analytic_base_department/LICENSE
odoo_addons/analytic_base_department/README.rst
odoo_addons/analytic_base_department/__init__.py
odoo_addons/analytic_base_department/__openerp__.py
odoo_addons/analytic_base_department/i18n/analytic_base_department.pot
odoo_addons/analytic_base_department/i18n/ca.po
odoo_addons/analytic_base_department/i18n/de.po
odoo_addons/analytic_base_department/i18n/el_GR.po
odoo_addons/analytic_base_department/i18n/es.po
odoo_addons/analytic_base_department/i18n/es_MX.po
odoo_addons/analytic_base_department/i18n/fi.po
odoo_addons/analytic_base_department/i18n/fr.po
odoo_addons/analytic_base_department/i18n/gl.po
odoo_addons/analytic_base_department/i18n/hr.po
odoo_addons/analytic_base_department/i18n/hr_HR.po
odoo_addons/analytic_base_department/i18n/hu.po
odoo_addons/analytic_base_department/i18n/it.po
odoo_addons/analytic_base_department/i18n/nl.po
odoo_addons/analytic_base_department/i18n/pt.po
odoo_addons/analytic_base_department/i18n/pt_BR.po
odoo_addons/analytic_base_department/i18n/pt_PT.po
odoo_addons/analytic_base_department/i18n/ro.po
odoo_addons/analytic_base_department/i18n/sk_SK.po
odoo_addons/analytic_base_department/i18n/sl.po
odoo_addons/analytic_base_department/models/__init__.py
odoo_addons/analytic_base_department/models/analytic.py
odoo_addons/analytic_base_department/static/description/icon.png
odoo_addons/analytic_base_department/tests/__init__.py
odoo_addons/analytic_base_department/tests/test_line_department.py
odoo_addons/analytic_base_department/views/analytic.xml
odoo9_addon_analytic_base_department-9.0.1.0.0.99.dev17.dist-info/METADATA
odoo9_addon_analytic_base_department-9.0.1.0.0.99.dev17.dist-info/WHEEL
odoo9_addon_analytic_base_department-9.0.1.0.0.99.dev17.dist-info/namespace_packages.txt
odoo9_addon_analytic_base_department-9.0.1.0.0.99.dev17.dist-info/top_level.txt
odoo9_addon_analytic_base_department-9.0.1.0.0.99.dev17.dist-info/RECORD
